SPACEL/__init__.py
SPACEL/_version.py
SPACEL/setting.py
SPACEL/Scube/__init__.py
SPACEL/Scube/alignment.py
SPACEL/Scube/gpr.py
SPACEL/Scube/plot.py
SPACEL/Scube/utils_3d.py
SPACEL/Splane/__init__.py
SPACEL/Splane/base_model.py
SPACEL/Splane/graph.py
SPACEL/Splane/model.py
SPACEL/Splane/pygcn_utils.py
SPACEL/Splane/utils.py
SPACEL/Splane/kegra/__init__.py
SPACEL/Splane/kegra/gnn.py
SPACEL/Splane/kegra/gnn_utils.py
SPACEL/Spoint/__init__.py
SPACEL/Spoint/base_model.py
SPACEL/Spoint/data_augmentation.py
SPACEL/Spoint/data_downsample.py
SPACEL/Spoint/data_utils.py
SPACEL/Spoint/metrics.py
SPACEL/Spoint/model.py
SPACEL/Spoint/spatial_simulation.py
SPACEL-1.1.8.dist-info/METADATA
SPACEL-1.1.8.dist-info/WHEEL
SPACEL-1.1.8.dist-info/top_level.txt
SPACEL-1.1.8.dist-info/RECORD
