Metadata-Version: 2.1
Name: SPACEL
Version: 1.1.8
Summary: SPACEL: characterizing spatial transcriptome architectures by deep-learning
Home-page: https://github.com/QuKunLab/SPACEL
Author: Hao Xu
Author-email: xuhaoustc@mail.ustc.edu.cn
Requires-Python: >=3.8
Requires-Dist: pip
Requires-Dist: squidpy (<1.3)
Requires-Dist: scvi-tools (<=0.20.3)
Requires-Dist: scikit-learn
Requires-Dist: scanpy
Requires-Dist: numba
Requires-Dist: torch (<=1.13)
Requires-Dist: gpytorch
Requires-Dist: optax (<=0.1.7)
